<solids xmlns:xsi="http://www.w3.org/2001/XMLSchema-instance"><polyhedra name="ALIC" startphi="45.0" deltaphi="360.0" numsides="4" aunit="deg" lunit="cm"><zplane rmin="0.0" rmax="2000.0" z="-15000.0"/><zplane rmin="0.0" rmax="2000.0" z="15000.0"/></polyhedra><box name="DCBA0x1" x="125.0" y="30.0" z="281.0" lunit="cm"/><box name="DCML0x1" x="50.0" y="61.0" z="281.0" lunit="cm"/><box name="DCH10x1" x="12.0" y="22.0" z="250.0" lunit="cm"/><box name="DCCV0x1" x="12.0" y="24.0" z="22.0" lunit="cm"/><tube name="DCC10x1" rmin="9.0" rmax="31.0" startphi="0.0" deltaphi="90.0" aunit="deg" z="12.0" lunit="cm"/><box name="DCMU0x1" x="16.0" y="31.0" z="250.0" lunit="cm"/><box name="DCH20x1" x="12.0" y="22.0" z="250.0" lunit="cm"/><box name="DCCV0x1001" x="12.0" y="24.0" z="22.0" lunit="cm"/><tube name="DCC10x1001" rmin="9.0" rmax="31.0" startphi="0.0" deltaphi="90.0" aunit="deg" z="12.0" lunit="cm"/><polyhedra name="DCLA0x1" startphi="0.0" deltaphi="90.0" numsides="1" aunit="deg" lunit="cm"><zplane rmin="0.0" rmax="24.75" z="-1.0"/><zplane rmin="0.0" rmax="24.75" z="1.0"/></polyhedra></solids>