<structure><volume name="SC14">
      <materialref ref="MUON_AIR"/>
      <solidref ref="SC140x1"/>
      <physvol name="SEA4V0_1" copynumber="1">
        <volumeref ref="SEA4V0"/>
        <positionref ref="SEA4V0_1inSC14pos"/>
        <rotationref ref="SEA4V0_1inSC14rot"/>
      </physvol>
      <physvol name="SEA4V1_1" copynumber="1">
        <volumeref ref="SEA4V1"/>
        <positionref ref="SEA4V1_1inSC14pos"/>
        <rotationref ref="SEA4V1_1inSC14rot"/>
      </physvol>
      <physvol name="SEA4V2_1" copynumber="1">
        <volumeref ref="SEA4V2"/>
        <positionref ref="SEA4V2_1inSC14pos"/>
        <rotationref ref="SEA4V2_1inSC14rot"/>
      </physvol>
      <physvol name="SEA4V3_1" copynumber="1">
        <volumeref ref="SEA4V3"/>
        <positionref ref="SEA4V3_1inSC14pos"/>
        <rotationref ref="SEA4V3_1inSC14rot"/>
      </physvol>
      <physvol name="SEA4V4_1" copynumber="1">
        <volumeref ref="SEA4V4"/>
        <positionref ref="SEA4V4_1inSC14pos"/>
        <rotationref ref="SEA4V4_1inSC14rot"/>
      </physvol>
      <physvol name="SEA4V5_1" copynumber="1">
        <volumeref ref="SEA4V5"/>
        <positionref ref="SEA4V5_1inSC14pos"/>
        <rotationref ref="SEA4V5_1inSC14rot"/>
      </physvol>
      <physvol name="SEA4V6_1" copynumber="1">
        <volumeref ref="SEA4V6"/>
        <positionref ref="SEA4V6_1inSC14pos"/>
        <rotationref ref="SEA4V6_1inSC14rot"/>
      </physvol>
      <physvol name="SEA4V7_1" copynumber="1">
        <volumeref ref="SEA4V7"/>
        <positionref ref="SEA4V7_1inSC14pos"/>
        <rotationref ref="SEA4V7_1inSC14rot"/>
      </physvol>
      <physvol name="S3R5_1" copynumber="1">
        <volumeref ref="S3R5"/>
        <positionref ref="S3R5_1inSC14pos"/>
      </physvol>
      <physvol name="S3L5_1" copynumber="1">
        <volumeref ref="S3L5"/>
        <positionref ref="S3L5_1inSC14pos"/>
        <rotationref ref="S3L5_1inSC14rot"/>
      </physvol>
      <physvol name="SA4HA0_1" copynumber="1">
        <volumeref ref="SA4HA0"/>
        <positionref ref="SA4HA0_1inSC14pos"/>
      </physvol>
      <physvol name="SA4HA3_1" copynumber="1">
        <volumeref ref="SA4HA3"/>
        <positionref ref="SA4HA3_1inSC14pos"/>
        <rotationref ref="SA4HA3_1inSC14rot"/>
      </physvol>
      <physvol name="SA4HA1_1" copynumber="1">
        <volumeref ref="SA4HA1"/>
        <positionref ref="SA4HA1_1inSC14pos"/>
      </physvol>
      <physvol name="SA4HA4_1" copynumber="1">
        <volumeref ref="SA4HA4"/>
        <positionref ref="SA4HA4_1inSC14pos"/>
        <rotationref ref="SA4HA4_1inSC14rot"/>
      </physvol>
      <physvol name="SA4HA2_1" copynumber="1">
        <volumeref ref="SA4HA2"/>
        <positionref ref="SA4HA2_1inSC14pos"/>
      </physvol>
      <physvol name="SA4HA5_1" copynumber="1">
        <volumeref ref="SA4HA5"/>
        <positionref ref="SA4HA5_1inSC14pos"/>
        <rotationref ref="SA4HA5_1inSC14rot"/>
      </physvol>
      <physvol name="SV14A0_1" copynumber="1">
        <volumeref ref="SV14A0"/>
        <positionref ref="SV14A0_1inSC14pos"/>
      </physvol>
      <physvol name="SV14A1_1" copynumber="1">
        <volumeref ref="SV14A1"/>
        <positionref ref="SV14A1_1inSC14pos"/>
        <rotationref ref="SV14A1_1inSC14rot"/>
      </physvol>
      <physvol name="SH14A0_1" copynumber="1">
        <volumeref ref="SH14A0"/>
        <positionref ref="SH14A0_1inSC14pos"/>
      </physvol>
      <physvol name="SH14A1_1" copynumber="1">
        <volumeref ref="SH14A1"/>
        <positionref ref="SH14A1_1inSC14pos"/>
        <rotationref ref="SH14A1_1inSC14rot"/>
      </physvol>
      <physvol name="SP14A0_1" copynumber="1">
        <volumeref ref="SP14A0"/>
        <positionref ref="SP14A0_1inSC14pos"/>
        <rotationref ref="SP14A0_1inSC14rot"/>
      </physvol>
      <physvol name="SP14A1_1" copynumber="1">
        <volumeref ref="SP14A1"/>
        <positionref ref="SP14A1_1inSC14pos"/>
        <rotationref ref="SP14A1_1inSC14rot"/>
      </physvol>
      <physvol name="SV24A0_1" copynumber="1">
        <volumeref ref="SV24A0"/>
        <positionref ref="SV24A0_1inSC14pos"/>
      </physvol>
      <physvol name="SV24A1_1" copynumber="1">
        <volumeref ref="SV24A1"/>
        <positionref ref="SV24A1_1inSC14pos"/>
        <rotationref ref="SV24A1_1inSC14rot"/>
      </physvol>
      <physvol name="SH24A0_1" copynumber="1">
        <volumeref ref="SH24A0"/>
        <positionref ref="SH24A0_1inSC14pos"/>
      </physvol>
      <physvol name="SH24A1_1" copynumber="1">
        <volumeref ref="SH24A1"/>
        <positionref ref="SH24A1_1inSC14pos"/>
        <rotationref ref="SH24A1_1inSC14rot"/>
      </physvol>
      <physvol name="SV34A0_1" copynumber="1">
        <volumeref ref="SV34A0"/>
        <positionref ref="SV34A0_1inSC14pos"/>
      </physvol>
      <physvol name="SV34A1_1" copynumber="1">
        <volumeref ref="SV34A1"/>
        <positionref ref="SV34A1_1inSC14pos"/>
        <rotationref ref="SV34A1_1inSC14rot"/>
      </physvol>
      <physvol name="SH34A0_1" copynumber="1">
        <volumeref ref="SH34A0"/>
        <positionref ref="SH34A0_1inSC14pos"/>
      </physvol>
      <physvol name="SH34A1_1" copynumber="1">
        <volumeref ref="SH34A1"/>
        <positionref ref="SH34A1_1inSC14pos"/>
        <rotationref ref="SH34A1_1inSC14rot"/>
      </physvol>
      <physvol name="SP24A0_1" copynumber="1">
        <volumeref ref="SP24A0"/>
        <positionref ref="SP24A0_1inSC14pos"/>
        <rotationref ref="SP24A0_1inSC14rot"/>
      </physvol>
      <physvol name="SP24A1_1" copynumber="1">
        <volumeref ref="SP24A1"/>
        <positionref ref="SP24A1_1inSC14pos"/>
        <rotationref ref="SP24A1_1inSC14rot"/>
      </physvol>
      <physvol name="SV44A0_1" copynumber="1">
        <volumeref ref="SV44A0"/>
        <positionref ref="SV44A0_1inSC14pos"/>
      </physvol>
      <physvol name="SV44A1_1" copynumber="1">
        <volumeref ref="SV44A1"/>
        <positionref ref="SV44A1_1inSC14pos"/>
        <rotationref ref="SV44A1_1inSC14rot"/>
      </physvol>
      <physvol name="SH44A0_1" copynumber="1">
        <volumeref ref="SH44A0"/>
        <positionref ref="SH44A0_1inSC14pos"/>
      </physvol>
      <physvol name="SH44A1_1" copynumber="1">
        <volumeref ref="SH44A1"/>
        <positionref ref="SH44A1_1inSC14pos"/>
        <rotationref ref="SH44A1_1inSC14rot"/>
      </physvol>
      <physvol name="SHX4A0_1" copynumber="1">
        <volumeref ref="SHX4A0"/>
        <positionref ref="SHX4A0_1inSC14pos"/>
      </physvol>
      <physvol name="SHX4A1_1" copynumber="1">
        <volumeref ref="SHX4A1"/>
        <positionref ref="SHX4A1_1inSC14pos"/>
        <rotationref ref="SHX4A1_1inSC14rot"/>
      </physvol>
      <physvol name="SVX4A0_1" copynumber="1">
        <volumeref ref="SVX4A0"/>
        <positionref ref="SVX4A0_1inSC14pos"/>
      </physvol>
      <physvol name="SVX4A1_1" copynumber="1">
        <volumeref ref="SVX4A1"/>
        <positionref ref="SVX4A1_1inSC14pos"/>
        <rotationref ref="SVX4A1_1inSC14rot"/>
      </physvol>
      <physvol name="S3R4_1" copynumber="1">
        <volumeref ref="S3R4"/>
        <positionref ref="S3R4_1inSC14pos"/>
      </physvol>
      <physvol name="S3R6_1" copynumber="1">
        <volumeref ref="S3R6"/>
        <positionref ref="S3R6_1inSC14pos"/>
      </physvol>
      <physvol name="S3L4_1" copynumber="1">
        <volumeref ref="S3L4"/>
        <positionref ref="S3L4_1inSC14pos"/>
        <rotationref ref="S3L4_1inSC14rot"/>
      </physvol>
      <physvol name="S3L6_1" copynumber="1">
        <volumeref ref="S3L6"/>
        <positionref ref="S3L6_1inSC14pos"/>
        <rotationref ref="S3L6_1inSC14rot"/>
      </physvol>
      <physvol name="SA4HB0_1" copynumber="1">
        <volumeref ref="SA4HB0"/>
        <positionref ref="SA4HB0_1inSC14pos"/>
      </physvol>
      <physvol name="SA4HB3_1" copynumber="1">
        <volumeref ref="SA4HB3"/>
        <positionref ref="SA4HB3_1inSC14pos"/>
      </physvol>
      <physvol name="SA4HB6_1" copynumber="1">
        <volumeref ref="SA4HB6"/>
        <positionref ref="SA4HB6_1inSC14pos"/>
        <rotationref ref="SA4HB6_1inSC14rot"/>
      </physvol>
      <physvol name="SA4HB9_1" copynumber="1">
        <volumeref ref="SA4HB9"/>
        <positionref ref="SA4HB9_1inSC14pos"/>
        <rotationref ref="SA4HB9_1inSC14rot"/>
      </physvol>
      <physvol name="SA4HB1_1" copynumber="1">
        <volumeref ref="SA4HB1"/>
        <positionref ref="SA4HB1_1inSC14pos"/>
      </physvol>
      <physvol name="SA4HB4_1" copynumber="1">
        <volumeref ref="SA4HB4"/>
        <positionref ref="SA4HB4_1inSC14pos"/>
      </physvol>
      <physvol name="SA4HB7_1" copynumber="1">
        <volumeref ref="SA4HB7"/>
        <positionref ref="SA4HB7_1inSC14pos"/>
        <rotationref ref="SA4HB7_1inSC14rot"/>
      </physvol>
      <physvol name="SA4HB10_1" copynumber="1">
        <volumeref ref="SA4HB10"/>
        <positionref ref="SA4HB10_1inSC14pos"/>
        <rotationref ref="SA4HB10_1inSC14rot"/>
      </physvol>
      <physvol name="SA4HB2_1" copynumber="1">
        <volumeref ref="SA4HB2"/>
        <positionref ref="SA4HB2_1inSC14pos"/>
      </physvol>
      <physvol name="SA4HB5_1" copynumber="1">
        <volumeref ref="SA4HB5"/>
        <positionref ref="SA4HB5_1inSC14pos"/>
      </physvol>
      <physvol name="SA4HB8_1" copynumber="1">
        <volumeref ref="SA4HB8"/>
        <positionref ref="SA4HB8_1inSC14pos"/>
        <rotationref ref="SA4HB8_1inSC14rot"/>
      </physvol>
      <physvol name="SA4HB11_1" copynumber="1">
        <volumeref ref="SA4HB11"/>
        <positionref ref="SA4HB11_1inSC14pos"/>
        <rotationref ref="SA4HB11_1inSC14rot"/>
      </physvol>
      <physvol name="SV14B0_1" copynumber="1">
        <volumeref ref="SV14B0"/>
        <positionref ref="SV14B0_1inSC14pos"/>
      </physvol>
      <physvol name="SV14B2_1" copynumber="1">
        <volumeref ref="SV14B2"/>
        <positionref ref="SV14B2_1inSC14pos"/>
        <rotationref ref="SV14B2_1inSC14rot"/>
      </physvol>
      <physvol name="SH14B0_1" copynumber="1">
        <volumeref ref="SH14B0"/>
        <positionref ref="SH14B0_1inSC14pos"/>
      </physvol>
      <physvol name="SH14B2_1" copynumber="1">
        <volumeref ref="SH14B2"/>
        <positionref ref="SH14B2_1inSC14pos"/>
        <rotationref ref="SH14B2_1inSC14rot"/>
      </physvol>
      <physvol name="SP14BC0_1" copynumber="1">
        <volumeref ref="SP14BC0"/>
        <positionref ref="SP14BC0_1inSC14pos"/>
        <rotationref ref="SP14BC0_1inSC14rot"/>
      </physvol>
      <physvol name="SP14BC2_1" copynumber="1">
        <volumeref ref="SP14BC2"/>
        <positionref ref="SP14BC2_1inSC14pos"/>
        <rotationref ref="SP14BC2_1inSC14rot"/>
      </physvol>
      <physvol name="SV24B0_1" copynumber="1">
        <volumeref ref="SV24B0"/>
        <positionref ref="SV24B0_1inSC14pos"/>
      </physvol>
      <physvol name="SV24B2_1" copynumber="1">
        <volumeref ref="SV24B2"/>
        <positionref ref="SV24B2_1inSC14pos"/>
        <rotationref ref="SV24B2_1inSC14rot"/>
      </physvol>
      <physvol name="SH24B0_1" copynumber="1">
        <volumeref ref="SH24B0"/>
        <positionref ref="SH24B0_1inSC14pos"/>
      </physvol>
      <physvol name="SH24B2_1" copynumber="1">
        <volumeref ref="SH24B2"/>
        <positionref ref="SH24B2_1inSC14pos"/>
        <rotationref ref="SH24B2_1inSC14rot"/>
      </physvol>
      <physvol name="SV34B0_1" copynumber="1">
        <volumeref ref="SV34B0"/>
        <positionref ref="SV34B0_1inSC14pos"/>
      </physvol>
      <physvol name="SV34B2_1" copynumber="1">
        <volumeref ref="SV34B2"/>
        <positionref ref="SV34B2_1inSC14pos"/>
        <rotationref ref="SV34B2_1inSC14rot"/>
      </physvol>
      <physvol name="SH34B0_1" copynumber="1">
        <volumeref ref="SH34B0"/>
        <positionref ref="SH34B0_1inSC14pos"/>
      </physvol>
      <physvol name="SH34B2_1" copynumber="1">
        <volumeref ref="SH34B2"/>
        <positionref ref="SH34B2_1inSC14pos"/>
        <rotationref ref="SH34B2_1inSC14rot"/>
      </physvol>
      <physvol name="SP24BC0_1" copynumber="1">
        <volumeref ref="SP24BC0"/>
        <positionref ref="SP24BC0_1inSC14pos"/>
        <rotationref ref="SP24BC0_1inSC14rot"/>
      </physvol>
      <physvol name="SP24BC2_1" copynumber="1">
        <volumeref ref="SP24BC2"/>
        <positionref ref="SP24BC2_1inSC14pos"/>
        <rotationref ref="SP24BC2_1inSC14rot"/>
      </physvol>
      <physvol name="SV44B0_1" copynumber="1">
        <volumeref ref="SV44B0"/>
        <positionref ref="SV44B0_1inSC14pos"/>
      </physvol>
      <physvol name="SV44B2_1" copynumber="1">
        <volumeref ref="SV44B2"/>
        <positionref ref="SV44B2_1inSC14pos"/>
        <rotationref ref="SV44B2_1inSC14rot"/>
      </physvol>
      <physvol name="SH44B0_1" copynumber="1">
        <volumeref ref="SH44B0"/>
        <positionref ref="SH44B0_1inSC14pos"/>
      </physvol>
      <physvol name="SH44B2_1" copynumber="1">
        <volumeref ref="SH44B2"/>
        <positionref ref="SH44B2_1inSC14pos"/>
        <rotationref ref="SH44B2_1inSC14rot"/>
      </physvol>
      <physvol name="SHX4B0_1" copynumber="1">
        <volumeref ref="SHX4B0"/>
        <positionref ref="SHX4B0_1inSC14pos"/>
      </physvol>
      <physvol name="SHX4B2_1" copynumber="1">
        <volumeref ref="SHX4B2"/>
        <positionref ref="SHX4B2_1inSC14pos"/>
        <rotationref ref="SHX4B2_1inSC14rot"/>
      </physvol>
      <physvol name="SVX4B0_1" copynumber="1">
        <volumeref ref="SVX4B0"/>
        <positionref ref="SVX4B0_1inSC14pos"/>
      </physvol>
      <physvol name="SVX4B2_1" copynumber="1">
        <volumeref ref="SVX4B2"/>
        <positionref ref="SVX4B2_1inSC14pos"/>
        <rotationref ref="SVX4B2_1inSC14rot"/>
      </physvol>
      <physvol name="SV14B1_1" copynumber="1">
        <volumeref ref="SV14B1"/>
        <positionref ref="SV14B1_1inSC14pos"/>
      </physvol>
      <physvol name="SV14B3_1" copynumber="1">
        <volumeref ref="SV14B3"/>
        <positionref ref="SV14B3_1inSC14pos"/>
        <rotationref ref="SV14B3_1inSC14rot"/>
      </physvol>
      <physvol name="SH14B1_1" copynumber="1">
        <volumeref ref="SH14B1"/>
        <positionref ref="SH14B1_1inSC14pos"/>
      </physvol>
      <physvol name="SH14B3_1" copynumber="1">
        <volumeref ref="SH14B3"/>
        <positionref ref="SH14B3_1inSC14pos"/>
        <rotationref ref="SH14B3_1inSC14rot"/>
      </physvol>
      <physvol name="SP14BC1_1" copynumber="1">
        <volumeref ref="SP14BC1"/>
        <positionref ref="SP14BC1_1inSC14pos"/>
        <rotationref ref="SP14BC1_1inSC14rot"/>
      </physvol>
      <physvol name="SP14BC3_1" copynumber="1">
        <volumeref ref="SP14BC3"/>
        <positionref ref="SP14BC3_1inSC14pos"/>
        <rotationref ref="SP14BC3_1inSC14rot"/>
      </physvol>
      <physvol name="SV24B1_1" copynumber="1">
        <volumeref ref="SV24B1"/>
        <positionref ref="SV24B1_1inSC14pos"/>
      </physvol>
      <physvol name="SV24B3_1" copynumber="1">
        <volumeref ref="SV24B3"/>
        <positionref ref="SV24B3_1inSC14pos"/>
        <rotationref ref="SV24B3_1inSC14rot"/>
      </physvol>
      <physvol name="SH24B1_1" copynumber="1">
        <volumeref ref="SH24B1"/>
        <positionref ref="SH24B1_1inSC14pos"/>
      </physvol>
      <physvol name="SH24B3_1" copynumber="1">
        <volumeref ref="SH24B3"/>
        <positionref ref="SH24B3_1inSC14pos"/>
        <rotationref ref="SH24B3_1inSC14rot"/>
      </physvol>
      <physvol name="SV34B1_1" copynumber="1">
        <volumeref ref="SV34B1"/>
        <positionref ref="SV34B1_1inSC14pos"/>
      </physvol>
      <physvol name="SV34B3_1" copynumber="1">
        <volumeref ref="SV34B3"/>
        <positionref ref="SV34B3_1inSC14pos"/>
        <rotationref ref="SV34B3_1inSC14rot"/>
      </physvol>
      <physvol name="SH34B1_1" copynumber="1">
        <volumeref ref="SH34B1"/>
        <positionref ref="SH34B1_1inSC14pos"/>
      </physvol>
      <physvol name="SH34B3_1" copynumber="1">
        <volumeref ref="SH34B3"/>
        <positionref ref="SH34B3_1inSC14pos"/>
        <rotationref ref="SH34B3_1inSC14rot"/>
      </physvol>
      <physvol name="SP24BC1_1" copynumber="1">
        <volumeref ref="SP24BC1"/>
        <positionref ref="SP24BC1_1inSC14pos"/>
        <rotationref ref="SP24BC1_1inSC14rot"/>
      </physvol>
      <physvol name="SP24BC3_1" copynumber="1">
        <volumeref ref="SP24BC3"/>
        <positionref ref="SP24BC3_1inSC14pos"/>
        <rotationref ref="SP24BC3_1inSC14rot"/>
      </physvol>
      <physvol name="SV44B1_1" copynumber="1">
        <volumeref ref="SV44B1"/>
        <positionref ref="SV44B1_1inSC14pos"/>
      </physvol>
      <physvol name="SV44B3_1" copynumber="1">
        <volumeref ref="SV44B3"/>
        <positionref ref="SV44B3_1inSC14pos"/>
        <rotationref ref="SV44B3_1inSC14rot"/>
      </physvol>
      <physvol name="SH44B1_1" copynumber="1">
        <volumeref ref="SH44B1"/>
        <positionref ref="SH44B1_1inSC14pos"/>
      </physvol>
      <physvol name="SH44B3_1" copynumber="1">
        <volumeref ref="SH44B3"/>
        <positionref ref="SH44B3_1inSC14pos"/>
        <rotationref ref="SH44B3_1inSC14rot"/>
      </physvol>
      <physvol name="SHX4B1_1" copynumber="1">
        <volumeref ref="SHX4B1"/>
        <positionref ref="SHX4B1_1inSC14pos"/>
      </physvol>
      <physvol name="SHX4B3_1" copynumber="1">
        <volumeref ref="SHX4B3"/>
        <positionref ref="SHX4B3_1inSC14pos"/>
        <rotationref ref="SHX4B3_1inSC14rot"/>
      </physvol>
      <physvol name="SVX4B1_1" copynumber="1">
        <volumeref ref="SVX4B1"/>
        <positionref ref="SVX4B1_1inSC14pos"/>
      </physvol>
      <physvol name="SVX4B3_1" copynumber="1">
        <volumeref ref="SVX4B3"/>
        <positionref ref="SVX4B3_1inSC14pos"/>
        <rotationref ref="SVX4B3_1inSC14rot"/>
      </physvol>
      <physvol name="S3R3_1" copynumber="1">
        <volumeref ref="S3R3"/>
        <positionref ref="S3R3_1inSC14pos"/>
      </physvol>
      <physvol name="S3R7_1" copynumber="1">
        <volumeref ref="S3R7"/>
        <positionref ref="S3R7_1inSC14pos"/>
      </physvol>
      <physvol name="S3L3_1" copynumber="1">
        <volumeref ref="S3L3"/>
        <positionref ref="S3L3_1inSC14pos"/>
        <rotationref ref="S3L3_1inSC14rot"/>
      </physvol>
      <physvol name="S3L7_1" copynumber="1">
        <volumeref ref="S3L7"/>
        <positionref ref="S3L7_1inSC14pos"/>
        <rotationref ref="S3L7_1inSC14rot"/>
      </physvol>
      <physvol name="SA4HD0_1" copynumber="1">
        <volumeref ref="SA4HD0"/>
        <positionref ref="SA4HD0_1inSC14pos"/>
      </physvol>
      <physvol name="SA4HD3_1" copynumber="1">
        <volumeref ref="SA4HD3"/>
        <positionref ref="SA4HD3_1inSC14pos"/>
      </physvol>
      <physvol name="SA4HD6_1" copynumber="1">
        <volumeref ref="SA4HD6"/>
        <positionref ref="SA4HD6_1inSC14pos"/>
        <rotationref ref="SA4HD6_1inSC14rot"/>
      </physvol>
      <physvol name="SA4HD9_1" copynumber="1">
        <volumeref ref="SA4HD9"/>
        <positionref ref="SA4HD9_1inSC14pos"/>
        <rotationref ref="SA4HD9_1inSC14rot"/>
      </physvol>
      <physvol name="SA4HD1_1" copynumber="1">
        <volumeref ref="SA4HD1"/>
        <positionref ref="SA4HD1_1inSC14pos"/>
      </physvol>
      <physvol name="SA4HD4_1" copynumber="1">
        <volumeref ref="SA4HD4"/>
        <positionref ref="SA4HD4_1inSC14pos"/>
      </physvol>
      <physvol name="SA4HD7_1" copynumber="1">
        <volumeref ref="SA4HD7"/>
        <positionref ref="SA4HD7_1inSC14pos"/>
        <rotationref ref="SA4HD7_1inSC14rot"/>
      </physvol>
      <physvol name="SA4HD10_1" copynumber="1">
        <volumeref ref="SA4HD10"/>
        <positionref ref="SA4HD10_1inSC14pos"/>
        <rotationref ref="SA4HD10_1inSC14rot"/>
      </physvol>
      <physvol name="SA4HD2_1" copynumber="1">
        <volumeref ref="SA4HD2"/>
        <positionref ref="SA4HD2_1inSC14pos"/>
      </physvol>
      <physvol name="SA4HD5_1" copynumber="1">
        <volumeref ref="SA4HD5"/>
        <positionref ref="SA4HD5_1inSC14pos"/>
      </physvol>
      <physvol name="SA4HD8_1" copynumber="1">
        <volumeref ref="SA4HD8"/>
        <positionref ref="SA4HD8_1inSC14pos"/>
        <rotationref ref="SA4HD8_1inSC14rot"/>
      </physvol>
      <physvol name="SA4HD11_1" copynumber="1">
        <volumeref ref="SA4HD11"/>
        <positionref ref="SA4HD11_1inSC14pos"/>
        <rotationref ref="SA4HD11_1inSC14rot"/>
      </physvol>
      <physvol name="SV14D0_1" copynumber="1">
        <volumeref ref="SV14D0"/>
        <positionref ref="SV14D0_1inSC14pos"/>
      </physvol>
      <physvol name="SV14D1_1" copynumber="1">
        <volumeref ref="SV14D1"/>
        <positionref ref="SV14D1_1inSC14pos"/>
      </physvol>
      <physvol name="SV14D2_1" copynumber="1">
        <volumeref ref="SV14D2"/>
        <positionref ref="SV14D2_1inSC14pos"/>
        <rotationref ref="SV14D2_1inSC14rot"/>
      </physvol>
      <physvol name="SV14D3_1" copynumber="1">
        <volumeref ref="SV14D3"/>
        <positionref ref="SV14D3_1inSC14pos"/>
        <rotationref ref="SV14D3_1inSC14rot"/>
      </physvol>
      <physvol name="SH14D0_1" copynumber="1">
        <volumeref ref="SH14D0"/>
        <positionref ref="SH14D0_1inSC14pos"/>
      </physvol>
      <physvol name="SH14D1_1" copynumber="1">
        <volumeref ref="SH14D1"/>
        <positionref ref="SH14D1_1inSC14pos"/>
      </physvol>
      <physvol name="SH14D2_1" copynumber="1">
        <volumeref ref="SH14D2"/>
        <positionref ref="SH14D2_1inSC14pos"/>
        <rotationref ref="SH14D2_1inSC14rot"/>
      </physvol>
      <physvol name="SH14D3_1" copynumber="1">
        <volumeref ref="SH14D3"/>
        <positionref ref="SH14D3_1inSC14pos"/>
        <rotationref ref="SH14D3_1inSC14rot"/>
      </physvol>
      <physvol name="SP14D0_1" copynumber="1">
        <volumeref ref="SP14D0"/>
        <positionref ref="SP14D0_1inSC14pos"/>
        <rotationref ref="SP14D0_1inSC14rot"/>
      </physvol>
      <physvol name="SP14D1_1" copynumber="1">
        <volumeref ref="SP14D1"/>
        <positionref ref="SP14D1_1inSC14pos"/>
        <rotationref ref="SP14D1_1inSC14rot"/>
      </physvol>
      <physvol name="SP14D2_1" copynumber="1">
        <volumeref ref="SP14D2"/>
        <positionref ref="SP14D2_1inSC14pos"/>
        <rotationref ref="SP14D2_1inSC14rot"/>
      </physvol>
      <physvol name="SP14D3_1" copynumber="1">
        <volumeref ref="SP14D3"/>
        <positionref ref="SP14D3_1inSC14pos"/>
        <rotationref ref="SP14D3_1inSC14rot"/>
      </physvol>
      <physvol name="SV24D0_1" copynumber="1">
        <volumeref ref="SV24D0"/>
        <positionref ref="SV24D0_1inSC14pos"/>
      </physvol>
      <physvol name="SV24D1_1" copynumber="1">
        <volumeref ref="SV24D1"/>
        <positionref ref="SV24D1_1inSC14pos"/>
      </physvol>
      <physvol name="SV24D2_1" copynumber="1">
        <volumeref ref="SV24D2"/>
        <positionref ref="SV24D2_1inSC14pos"/>
        <rotationref ref="SV24D2_1inSC14rot"/>
      </physvol>
      <physvol name="SV24D3_1" copynumber="1">
        <volumeref ref="SV24D3"/>
        <positionref ref="SV24D3_1inSC14pos"/>
        <rotationref ref="SV24D3_1inSC14rot"/>
      </physvol>
      <physvol name="SH24D0_1" copynumber="1">
        <volumeref ref="SH24D0"/>
        <positionref ref="SH24D0_1inSC14pos"/>
      </physvol>
      <physvol name="SH24D1_1" copynumber="1">
        <volumeref ref="SH24D1"/>
        <positionref ref="SH24D1_1inSC14pos"/>
      </physvol>
      <physvol name="SH24D2_1" copynumber="1">
        <volumeref ref="SH24D2"/>
        <positionref ref="SH24D2_1inSC14pos"/>
        <rotationref ref="SH24D2_1inSC14rot"/>
      </physvol>
      <physvol name="SH24D3_1" copynumber="1">
        <volumeref ref="SH24D3"/>
        <positionref ref="SH24D3_1inSC14pos"/>
        <rotationref ref="SH24D3_1inSC14rot"/>
      </physvol>
      <physvol name="SV34D0_1" copynumber="1">
        <volumeref ref="SV34D0"/>
        <positionref ref="SV34D0_1inSC14pos"/>
      </physvol>
      <physvol name="SV34D1_1" copynumber="1">
        <volumeref ref="SV34D1"/>
        <positionref ref="SV34D1_1inSC14pos"/>
      </physvol>
      <physvol name="SV34D2_1" copynumber="1">
        <volumeref ref="SV34D2"/>
        <positionref ref="SV34D2_1inSC14pos"/>
        <rotationref ref="SV34D2_1inSC14rot"/>
      </physvol>
      <physvol name="SV34D3_1" copynumber="1">
        <volumeref ref="SV34D3"/>
        <positionref ref="SV34D3_1inSC14pos"/>
        <rotationref ref="SV34D3_1inSC14rot"/>
      </physvol>
      <physvol name="SH34D0_1" copynumber="1">
        <volumeref ref="SH34D0"/>
        <positionref ref="SH34D0_1inSC14pos"/>
      </physvol>
      <physvol name="SH34D1_1" copynumber="1">
        <volumeref ref="SH34D1"/>
        <positionref ref="SH34D1_1inSC14pos"/>
      </physvol>
      <physvol name="SH34D2_1" copynumber="1">
        <volumeref ref="SH34D2"/>
        <positionref ref="SH34D2_1inSC14pos"/>
        <rotationref ref="SH34D2_1inSC14rot"/>
      </physvol>
      <physvol name="SH34D3_1" copynumber="1">
        <volumeref ref="SH34D3"/>
        <positionref ref="SH34D3_1inSC14pos"/>
        <rotationref ref="SH34D3_1inSC14rot"/>
      </physvol>
      <physvol name="SP24D0_1" copynumber="1">
        <volumeref ref="SP24D0"/>
        <positionref ref="SP24D0_1inSC14pos"/>
        <rotationref ref="SP24D0_1inSC14rot"/>
      </physvol>
      <physvol name="SP24D1_1" copynumber="1">
        <volumeref ref="SP24D1"/>
        <positionref ref="SP24D1_1inSC14pos"/>
        <rotationref ref="SP24D1_1inSC14rot"/>
      </physvol>
      <physvol name="SP24D2_1" copynumber="1">
        <volumeref ref="SP24D2"/>
        <positionref ref="SP24D2_1inSC14pos"/>
        <rotationref ref="SP24D2_1inSC14rot"/>
      </physvol>
      <physvol name="SP24D3_1" copynumber="1">
        <volumeref ref="SP24D3"/>
        <positionref ref="SP24D3_1inSC14pos"/>
        <rotationref ref="SP24D3_1inSC14rot"/>
      </physvol>
      <physvol name="SV44D0_1" copynumber="1">
        <volumeref ref="SV44D0"/>
        <positionref ref="SV44D0_1inSC14pos"/>
      </physvol>
      <physvol name="SV44D1_1" copynumber="1">
        <volumeref ref="SV44D1"/>
        <positionref ref="SV44D1_1inSC14pos"/>
      </physvol>
      <physvol name="SV44D2_1" copynumber="1">
        <volumeref ref="SV44D2"/>
        <positionref ref="SV44D2_1inSC14pos"/>
        <rotationref ref="SV44D2_1inSC14rot"/>
      </physvol>
      <physvol name="SV44D3_1" copynumber="1">
        <volumeref ref="SV44D3"/>
        <positionref ref="SV44D3_1inSC14pos"/>
        <rotationref ref="SV44D3_1inSC14rot"/>
      </physvol>
      <physvol name="SH44D0_1" copynumber="1">
        <volumeref ref="SH44D0"/>
        <positionref ref="SH44D0_1inSC14pos"/>
      </physvol>
      <physvol name="SH44D1_1" copynumber="1">
        <volumeref ref="SH44D1"/>
        <positionref ref="SH44D1_1inSC14pos"/>
      </physvol>
      <physvol name="SH44D2_1" copynumber="1">
        <volumeref ref="SH44D2"/>
        <positionref ref="SH44D2_1inSC14pos"/>
        <rotationref ref="SH44D2_1inSC14rot"/>
      </physvol>
      <physvol name="SH44D3_1" copynumber="1">
        <volumeref ref="SH44D3"/>
        <positionref ref="SH44D3_1inSC14pos"/>
        <rotationref ref="SH44D3_1inSC14rot"/>
      </physvol>
      <physvol name="SHX4D0_1" copynumber="1">
        <volumeref ref="SHX4D0"/>
        <positionref ref="SHX4D0_1inSC14pos"/>
      </physvol>
      <physvol name="SHX4D1_1" copynumber="1">
        <volumeref ref="SHX4D1"/>
        <positionref ref="SHX4D1_1inSC14pos"/>
      </physvol>
      <physvol name="SHX4D2_1" copynumber="1">
        <volumeref ref="SHX4D2"/>
        <positionref ref="SHX4D2_1inSC14pos"/>
        <rotationref ref="SHX4D2_1inSC14rot"/>
      </physvol>
      <physvol name="SHX4D3_1" copynumber="1">
        <volumeref ref="SHX4D3"/>
        <positionref ref="SHX4D3_1inSC14pos"/>
        <rotationref ref="SHX4D3_1inSC14rot"/>
      </physvol>
      <physvol name="SVX4D0_1" copynumber="1">
        <volumeref ref="SVX4D0"/>
        <positionref ref="SVX4D0_1inSC14pos"/>
      </physvol>
      <physvol name="SVX4D1_1" copynumber="1">
        <volumeref ref="SVX4D1"/>
        <positionref ref="SVX4D1_1inSC14pos"/>
      </physvol>
      <physvol name="SVX4D2_1" copynumber="1">
        <volumeref ref="SVX4D2"/>
        <positionref ref="SVX4D2_1inSC14pos"/>
        <rotationref ref="SVX4D2_1inSC14rot"/>
      </physvol>
      <physvol name="SVX4D3_1" copynumber="1">
        <volumeref ref="SVX4D3"/>
        <positionref ref="SVX4D3_1inSC14pos"/>
        <rotationref ref="SVX4D3_1inSC14rot"/>
      </physvol>
      <physvol name="S3R2_1" copynumber="1">
        <volumeref ref="S3R2"/>
        <positionref ref="S3R2_1inSC14pos"/>
      </physvol>
      <physvol name="S3R8_1" copynumber="1">
        <volumeref ref="S3R8"/>
        <positionref ref="S3R8_1inSC14pos"/>
      </physvol>
      <physvol name="S3L2_1" copynumber="1">
        <volumeref ref="S3L2"/>
        <positionref ref="S3L2_1inSC14pos"/>
        <rotationref ref="S3L2_1inSC14rot"/>
      </physvol>
      <physvol name="S3L8_1" copynumber="1">
        <volumeref ref="S3L8"/>
        <positionref ref="S3L8_1inSC14pos"/>
        <rotationref ref="S3L8_1inSC14rot"/>
      </physvol>
      <physvol name="SA4HE0_1" copynumber="1">
        <volumeref ref="SA4HE0"/>
        <positionref ref="SA4HE0_1inSC14pos"/>
      </physvol>
      <physvol name="SA4HE3_1" copynumber="1">
        <volumeref ref="SA4HE3"/>
        <positionref ref="SA4HE3_1inSC14pos"/>
      </physvol>
      <physvol name="SA4HE6_1" copynumber="1">
        <volumeref ref="SA4HE6"/>
        <positionref ref="SA4HE6_1inSC14pos"/>
        <rotationref ref="SA4HE6_1inSC14rot"/>
      </physvol>
      <physvol name="SA4HE9_1" copynumber="1">
        <volumeref ref="SA4HE9"/>
        <positionref ref="SA4HE9_1inSC14pos"/>
        <rotationref ref="SA4HE9_1inSC14rot"/>
      </physvol>
      <physvol name="SA4HE1_1" copynumber="1">
        <volumeref ref="SA4HE1"/>
        <positionref ref="SA4HE1_1inSC14pos"/>
      </physvol>
      <physvol name="SA4HE4_1" copynumber="1">
        <volumeref ref="SA4HE4"/>
        <positionref ref="SA4HE4_1inSC14pos"/>
      </physvol>
      <physvol name="SA4HE7_1" copynumber="1">
        <volumeref ref="SA4HE7"/>
        <positionref ref="SA4HE7_1inSC14pos"/>
        <rotationref ref="SA4HE7_1inSC14rot"/>
      </physvol>
      <physvol name="SA4HE10_1" copynumber="1">
        <volumeref ref="SA4HE10"/>
        <positionref ref="SA4HE10_1inSC14pos"/>
        <rotationref ref="SA4HE10_1inSC14rot"/>
      </physvol>
      <physvol name="SA4HE2_1" copynumber="1">
        <volumeref ref="SA4HE2"/>
        <positionref ref="SA4HE2_1inSC14pos"/>
      </physvol>
      <physvol name="SA4HE5_1" copynumber="1">
        <volumeref ref="SA4HE5"/>
        <positionref ref="SA4HE5_1inSC14pos"/>
      </physvol>
      <physvol name="SA4HE8_1" copynumber="1">
        <volumeref ref="SA4HE8"/>
        <positionref ref="SA4HE8_1inSC14pos"/>
        <rotationref ref="SA4HE8_1inSC14rot"/>
      </physvol>
      <physvol name="SA4HE11_1" copynumber="1">
        <volumeref ref="SA4HE11"/>
        <positionref ref="SA4HE11_1inSC14pos"/>
        <rotationref ref="SA4HE11_1inSC14rot"/>
      </physvol>
      <physvol name="SV14E0_1" copynumber="1">
        <volumeref ref="SV14E0"/>
        <positionref ref="SV14E0_1inSC14pos"/>
      </physvol>
      <physvol name="SV14E1_1" copynumber="1">
        <volumeref ref="SV14E1"/>
        <positionref ref="SV14E1_1inSC14pos"/>
      </physvol>
      <physvol name="SV14E2_1" copynumber="1">
        <volumeref ref="SV14E2"/>
        <positionref ref="SV14E2_1inSC14pos"/>
        <rotationref ref="SV14E2_1inSC14rot"/>
      </physvol>
      <physvol name="SV14E3_1" copynumber="1">
        <volumeref ref="SV14E3"/>
        <positionref ref="SV14E3_1inSC14pos"/>
        <rotationref ref="SV14E3_1inSC14rot"/>
      </physvol>
      <physvol name="SH14E0_1" copynumber="1">
        <volumeref ref="SH14E0"/>
        <positionref ref="SH14E0_1inSC14pos"/>
      </physvol>
      <physvol name="SH14E1_1" copynumber="1">
        <volumeref ref="SH14E1"/>
        <positionref ref="SH14E1_1inSC14pos"/>
      </physvol>
      <physvol name="SH14E2_1" copynumber="1">
        <volumeref ref="SH14E2"/>
        <positionref ref="SH14E2_1inSC14pos"/>
        <rotationref ref="SH14E2_1inSC14rot"/>
      </physvol>
      <physvol name="SH14E3_1" copynumber="1">
        <volumeref ref="SH14E3"/>
        <positionref ref="SH14E3_1inSC14pos"/>
        <rotationref ref="SH14E3_1inSC14rot"/>
      </physvol>
      <physvol name="SP14E0_1" copynumber="1">
        <volumeref ref="SP14E0"/>
        <positionref ref="SP14E0_1inSC14pos"/>
        <rotationref ref="SP14E0_1inSC14rot"/>
      </physvol>
      <physvol name="SP14E1_1" copynumber="1">
        <volumeref ref="SP14E1"/>
        <positionref ref="SP14E1_1inSC14pos"/>
        <rotationref ref="SP14E1_1inSC14rot"/>
      </physvol>
      <physvol name="SP14E2_1" copynumber="1">
        <volumeref ref="SP14E2"/>
        <positionref ref="SP14E2_1inSC14pos"/>
        <rotationref ref="SP14E2_1inSC14rot"/>
      </physvol>
      <physvol name="SP14E3_1" copynumber="1">
        <volumeref ref="SP14E3"/>
        <positionref ref="SP14E3_1inSC14pos"/>
        <rotationref ref="SP14E3_1inSC14rot"/>
      </physvol>
      <physvol name="SV24E0_1" copynumber="1">
        <volumeref ref="SV24E0"/>
        <positionref ref="SV24E0_1inSC14pos"/>
      </physvol>
      <physvol name="SV24E1_1" copynumber="1">
        <volumeref ref="SV24E1"/>
        <positionref ref="SV24E1_1inSC14pos"/>
      </physvol>
      <physvol name="SV24E2_1" copynumber="1">
        <volumeref ref="SV24E2"/>
        <positionref ref="SV24E2_1inSC14pos"/>
        <rotationref ref="SV24E2_1inSC14rot"/>
      </physvol>
      <physvol name="SV24E3_1" copynumber="1">
        <volumeref ref="SV24E3"/>
        <positionref ref="SV24E3_1inSC14pos"/>
        <rotationref ref="SV24E3_1inSC14rot"/>
      </physvol>
      <physvol name="SH24E0_1" copynumber="1">
        <volumeref ref="SH24E0"/>
        <positionref ref="SH24E0_1inSC14pos"/>
      </physvol>
      <physvol name="SH24E1_1" copynumber="1">
        <volumeref ref="SH24E1"/>
        <positionref ref="SH24E1_1inSC14pos"/>
      </physvol>
      <physvol name="SH24E2_1" copynumber="1">
        <volumeref ref="SH24E2"/>
        <positionref ref="SH24E2_1inSC14pos"/>
        <rotationref ref="SH24E2_1inSC14rot"/>
      </physvol>
      <physvol name="SH24E3_1" copynumber="1">
        <volumeref ref="SH24E3"/>
        <positionref ref="SH24E3_1inSC14pos"/>
        <rotationref ref="SH24E3_1inSC14rot"/>
      </physvol>
      <physvol name="SV34E0_1" copynumber="1">
        <volumeref ref="SV34E0"/>
        <positionref ref="SV34E0_1inSC14pos"/>
      </physvol>
      <physvol name="SV34E1_1" copynumber="1">
        <volumeref ref="SV34E1"/>
        <positionref ref="SV34E1_1inSC14pos"/>
      </physvol>
      <physvol name="SV34E2_1" copynumber="1">
        <volumeref ref="SV34E2"/>
        <positionref ref="SV34E2_1inSC14pos"/>
        <rotationref ref="SV34E2_1inSC14rot"/>
      </physvol>
      <physvol name="SV34E3_1" copynumber="1">
        <volumeref ref="SV34E3"/>
        <positionref ref="SV34E3_1inSC14pos"/>
        <rotationref ref="SV34E3_1inSC14rot"/>
      </physvol>
      <physvol name="SH34E0_1" copynumber="1">
        <volumeref ref="SH34E0"/>
        <positionref ref="SH34E0_1inSC14pos"/>
      </physvol>
      <physvol name="SH34E1_1" copynumber="1">
        <volumeref ref="SH34E1"/>
        <positionref ref="SH34E1_1inSC14pos"/>
      </physvol>
      <physvol name="SH34E2_1" copynumber="1">
        <volumeref ref="SH34E2"/>
        <positionref ref="SH34E2_1inSC14pos"/>
        <rotationref ref="SH34E2_1inSC14rot"/>
      </physvol>
      <physvol name="SH34E3_1" copynumber="1">
        <volumeref ref="SH34E3"/>
        <positionref ref="SH34E3_1inSC14pos"/>
        <rotationref ref="SH34E3_1inSC14rot"/>
      </physvol>
      <physvol name="SP24E0_1" copynumber="1">
        <volumeref ref="SP24E0"/>
        <positionref ref="SP24E0_1inSC14pos"/>
        <rotationref ref="SP24E0_1inSC14rot"/>
      </physvol>
      <physvol name="SP24E1_1" copynumber="1">
        <volumeref ref="SP24E1"/>
        <positionref ref="SP24E1_1inSC14pos"/>
        <rotationref ref="SP24E1_1inSC14rot"/>
      </physvol>
      <physvol name="SP24E2_1" copynumber="1">
        <volumeref ref="SP24E2"/>
        <positionref ref="SP24E2_1inSC14pos"/>
        <rotationref ref="SP24E2_1inSC14rot"/>
      </physvol>
      <physvol name="SP24E3_1" copynumber="1">
        <volumeref ref="SP24E3"/>
        <positionref ref="SP24E3_1inSC14pos"/>
        <rotationref ref="SP24E3_1inSC14rot"/>
      </physvol>
      <physvol name="SV44E0_1" copynumber="1">
        <volumeref ref="SV44E0"/>
        <positionref ref="SV44E0_1inSC14pos"/>
      </physvol>
      <physvol name="SV44E1_1" copynumber="1">
        <volumeref ref="SV44E1"/>
        <positionref ref="SV44E1_1inSC14pos"/>
      </physvol>
      <physvol name="SV44E2_1" copynumber="1">
        <volumeref ref="SV44E2"/>
        <positionref ref="SV44E2_1inSC14pos"/>
        <rotationref ref="SV44E2_1inSC14rot"/>
      </physvol>
      <physvol name="SV44E3_1" copynumber="1">
        <volumeref ref="SV44E3"/>
        <positionref ref="SV44E3_1inSC14pos"/>
        <rotationref ref="SV44E3_1inSC14rot"/>
      </physvol>
      <physvol name="SH44E0_1" copynumber="1">
        <volumeref ref="SH44E0"/>
        <positionref ref="SH44E0_1inSC14pos"/>
      </physvol>
      <physvol name="SH44E1_1" copynumber="1">
        <volumeref ref="SH44E1"/>
        <positionref ref="SH44E1_1inSC14pos"/>
      </physvol>
      <physvol name="SH44E2_1" copynumber="1">
        <volumeref ref="SH44E2"/>
        <positionref ref="SH44E2_1inSC14pos"/>
        <rotationref ref="SH44E2_1inSC14rot"/>
      </physvol>
      <physvol name="SH44E3_1" copynumber="1">
        <volumeref ref="SH44E3"/>
        <positionref ref="SH44E3_1inSC14pos"/>
        <rotationref ref="SH44E3_1inSC14rot"/>
      </physvol>
      <physvol name="SHX4E0_1" copynumber="1">
        <volumeref ref="SHX4E0"/>
        <positionref ref="SHX4E0_1inSC14pos"/>
      </physvol>
      <physvol name="SHX4E1_1" copynumber="1">
        <volumeref ref="SHX4E1"/>
        <positionref ref="SHX4E1_1inSC14pos"/>
      </physvol>
      <physvol name="SHX4E2_1" copynumber="1">
        <volumeref ref="SHX4E2"/>
        <positionref ref="SHX4E2_1inSC14pos"/>
        <rotationref ref="SHX4E2_1inSC14rot"/>
      </physvol>
      <physvol name="SHX4E3_1" copynumber="1">
        <volumeref ref="SHX4E3"/>
        <positionref ref="SHX4E3_1inSC14pos"/>
        <rotationref ref="SHX4E3_1inSC14rot"/>
      </physvol>
      <physvol name="SVX4E0_1" copynumber="1">
        <volumeref ref="SVX4E0"/>
        <positionref ref="SVX4E0_1inSC14pos"/>
      </physvol>
      <physvol name="SVX4E1_1" copynumber="1">
        <volumeref ref="SVX4E1"/>
        <positionref ref="SVX4E1_1inSC14pos"/>
      </physvol>
      <physvol name="SVX4E2_1" copynumber="1">
        <volumeref ref="SVX4E2"/>
        <positionref ref="SVX4E2_1inSC14pos"/>
        <rotationref ref="SVX4E2_1inSC14rot"/>
      </physvol>
      <physvol name="SVX4E3_1" copynumber="1">
        <volumeref ref="SVX4E3"/>
        <positionref ref="SVX4E3_1inSC14pos"/>
        <rotationref ref="SVX4E3_1inSC14rot"/>
      </physvol>
      <physvol name="S3R1_1" copynumber="1">
        <volumeref ref="S3R1"/>
        <positionref ref="S3R1_1inSC14pos"/>
      </physvol>
      <physvol name="S3R9_1" copynumber="1">
        <volumeref ref="S3R9"/>
        <positionref ref="S3R9_1inSC14pos"/>
      </physvol>
      <physvol name="S3L1_1" copynumber="1">
        <volumeref ref="S3L1"/>
        <positionref ref="S3L1_1inSC14pos"/>
        <rotationref ref="S3L1_1inSC14rot"/>
      </physvol>
      <physvol name="S3L9_1" copynumber="1">
        <volumeref ref="S3L9"/>
        <positionref ref="S3L9_1inSC14pos"/>
        <rotationref ref="S3L9_1inSC14rot"/>
      </physvol>
      <physvol name="SA4HF0_1" copynumber="1">
        <volumeref ref="SA4HF0"/>
        <positionref ref="SA4HF0_1inSC14pos"/>
      </physvol>
      <physvol name="SA4HF3_1" copynumber="1">
        <volumeref ref="SA4HF3"/>
        <positionref ref="SA4HF3_1inSC14pos"/>
      </physvol>
      <physvol name="SA4HF6_1" copynumber="1">
        <volumeref ref="SA4HF6"/>
        <positionref ref="SA4HF6_1inSC14pos"/>
        <rotationref ref="SA4HF6_1inSC14rot"/>
      </physvol>
      <physvol name="SA4HF9_1" copynumber="1">
        <volumeref ref="SA4HF9"/>
        <positionref ref="SA4HF9_1inSC14pos"/>
        <rotationref ref="SA4HF9_1inSC14rot"/>
      </physvol>
      <physvol name="SA4HF1_1" copynumber="1">
        <volumeref ref="SA4HF1"/>
        <positionref ref="SA4HF1_1inSC14pos"/>
      </physvol>
      <physvol name="SA4HF4_1" copynumber="1">
        <volumeref ref="SA4HF4"/>
        <positionref ref="SA4HF4_1inSC14pos"/>
      </physvol>
      <physvol name="SA4HF7_1" copynumber="1">
        <volumeref ref="SA4HF7"/>
        <positionref ref="SA4HF7_1inSC14pos"/>
        <rotationref ref="SA4HF7_1inSC14rot"/>
      </physvol>
      <physvol name="SA4HF10_1" copynumber="1">
        <volumeref ref="SA4HF10"/>
        <positionref ref="SA4HF10_1inSC14pos"/>
        <rotationref ref="SA4HF10_1inSC14rot"/>
      </physvol>
      <physvol name="SA4HF2_1" copynumber="1">
        <volumeref ref="SA4HF2"/>
        <positionref ref="SA4HF2_1inSC14pos"/>
      </physvol>
      <physvol name="SA4HF5_1" copynumber="1">
        <volumeref ref="SA4HF5"/>
        <positionref ref="SA4HF5_1inSC14pos"/>
      </physvol>
      <physvol name="SA4HF8_1" copynumber="1">
        <volumeref ref="SA4HF8"/>
        <positionref ref="SA4HF8_1inSC14pos"/>
        <rotationref ref="SA4HF8_1inSC14rot"/>
      </physvol>
      <physvol name="SA4HF11_1" copynumber="1">
        <volumeref ref="SA4HF11"/>
        <positionref ref="SA4HF11_1inSC14pos"/>
        <rotationref ref="SA4HF11_1inSC14rot"/>
      </physvol>
      <physvol name="SV14F0_1" copynumber="1">
        <volumeref ref="SV14F0"/>
        <positionref ref="SV14F0_1inSC14pos"/>
      </physvol>
      <physvol name="SV14F1_1" copynumber="1">
        <volumeref ref="SV14F1"/>
        <positionref ref="SV14F1_1inSC14pos"/>
      </physvol>
      <physvol name="SV14F2_1" copynumber="1">
        <volumeref ref="SV14F2"/>
        <positionref ref="SV14F2_1inSC14pos"/>
        <rotationref ref="SV14F2_1inSC14rot"/>
      </physvol>
      <physvol name="SV14F3_1" copynumber="1">
        <volumeref ref="SV14F3"/>
        <positionref ref="SV14F3_1inSC14pos"/>
        <rotationref ref="SV14F3_1inSC14rot"/>
      </physvol>
      <physvol name="SH14F0_1" copynumber="1">
        <volumeref ref="SH14F0"/>
        <positionref ref="SH14F0_1inSC14pos"/>
      </physvol>
      <physvol name="SH14F1_1" copynumber="1">
        <volumeref ref="SH14F1"/>
        <positionref ref="SH14F1_1inSC14pos"/>
      </physvol>
      <physvol name="SH14F2_1" copynumber="1">
        <volumeref ref="SH14F2"/>
        <positionref ref="SH14F2_1inSC14pos"/>
        <rotationref ref="SH14F2_1inSC14rot"/>
      </physvol>
      <physvol name="SH14F3_1" copynumber="1">
        <volumeref ref="SH14F3"/>
        <positionref ref="SH14F3_1inSC14pos"/>
        <rotationref ref="SH14F3_1inSC14rot"/>
      </physvol>
      <physvol name="SP14F0_1" copynumber="1">
        <volumeref ref="SP14F0"/>
        <positionref ref="SP14F0_1inSC14pos"/>
        <rotationref ref="SP14F0_1inSC14rot"/>
      </physvol>
      <physvol name="SP14F1_1" copynumber="1">
        <volumeref ref="SP14F1"/>
        <positionref ref="SP14F1_1inSC14pos"/>
        <rotationref ref="SP14F1_1inSC14rot"/>
      </physvol>
      <physvol name="SP14F2_1" copynumber="1">
        <volumeref ref="SP14F2"/>
        <positionref ref="SP14F2_1inSC14pos"/>
        <rotationref ref="SP14F2_1inSC14rot"/>
      </physvol>
      <physvol name="SP14F3_1" copynumber="1">
        <volumeref ref="SP14F3"/>
        <positionref ref="SP14F3_1inSC14pos"/>
        <rotationref ref="SP14F3_1inSC14rot"/>
      </physvol>
      <physvol name="SV24F0_1" copynumber="1">
        <volumeref ref="SV24F0"/>
        <positionref ref="SV24F0_1inSC14pos"/>
      </physvol>
      <physvol name="SV24F1_1" copynumber="1">
        <volumeref ref="SV24F1"/>
        <positionref ref="SV24F1_1inSC14pos"/>
      </physvol>
      <physvol name="SV24F2_1" copynumber="1">
        <volumeref ref="SV24F2"/>
        <positionref ref="SV24F2_1inSC14pos"/>
        <rotationref ref="SV24F2_1inSC14rot"/>
      </physvol>
      <physvol name="SV24F3_1" copynumber="1">
        <volumeref ref="SV24F3"/>
        <positionref ref="SV24F3_1inSC14pos"/>
        <rotationref ref="SV24F3_1inSC14rot"/>
      </physvol>
      <physvol name="SH24F0_1" copynumber="1">
        <volumeref ref="SH24F0"/>
        <positionref ref="SH24F0_1inSC14pos"/>
      </physvol>
      <physvol name="SH24F1_1" copynumber="1">
        <volumeref ref="SH24F1"/>
        <positionref ref="SH24F1_1inSC14pos"/>
      </physvol>
      <physvol name="SH24F2_1" copynumber="1">
        <volumeref ref="SH24F2"/>
        <positionref ref="SH24F2_1inSC14pos"/>
        <rotationref ref="SH24F2_1inSC14rot"/>
      </physvol>
      <physvol name="SH24F3_1" copynumber="1">
        <volumeref ref="SH24F3"/>
        <positionref ref="SH24F3_1inSC14pos"/>
        <rotationref ref="SH24F3_1inSC14rot"/>
      </physvol>
      <physvol name="SV34F0_1" copynumber="1">
        <volumeref ref="SV34F0"/>
        <positionref ref="SV34F0_1inSC14pos"/>
      </physvol>
      <physvol name="SV34F1_1" copynumber="1">
        <volumeref ref="SV34F1"/>
        <positionref ref="SV34F1_1inSC14pos"/>
      </physvol>
      <physvol name="SV34F2_1" copynumber="1">
        <volumeref ref="SV34F2"/>
        <positionref ref="SV34F2_1inSC14pos"/>
        <rotationref ref="SV34F2_1inSC14rot"/>
      </physvol>
      <physvol name="SV34F3_1" copynumber="1">
        <volumeref ref="SV34F3"/>
        <positionref ref="SV34F3_1inSC14pos"/>
        <rotationref ref="SV34F3_1inSC14rot"/>
      </physvol>
      <physvol name="SH34F0_1" copynumber="1">
        <volumeref ref="SH34F0"/>
        <positionref ref="SH34F0_1inSC14pos"/>
      </physvol>
      <physvol name="SH34F1_1" copynumber="1">
        <volumeref ref="SH34F1"/>
        <positionref ref="SH34F1_1inSC14pos"/>
      </physvol>
      <physvol name="SH34F2_1" copynumber="1">
        <volumeref ref="SH34F2"/>
        <positionref ref="SH34F2_1inSC14pos"/>
        <rotationref ref="SH34F2_1inSC14rot"/>
      </physvol>
      <physvol name="SH34F3_1" copynumber="1">
        <volumeref ref="SH34F3"/>
        <positionref ref="SH34F3_1inSC14pos"/>
        <rotationref ref="SH34F3_1inSC14rot"/>
      </physvol>
      <physvol name="SP24F0_1" copynumber="1">
        <volumeref ref="SP24F0"/>
        <positionref ref="SP24F0_1inSC14pos"/>
        <rotationref ref="SP24F0_1inSC14rot"/>
      </physvol>
      <physvol name="SP24F1_1" copynumber="1">
        <volumeref ref="SP24F1"/>
        <positionref ref="SP24F1_1inSC14pos"/>
        <rotationref ref="SP24F1_1inSC14rot"/>
      </physvol>
      <physvol name="SP24F2_1" copynumber="1">
        <volumeref ref="SP24F2"/>
        <positionref ref="SP24F2_1inSC14pos"/>
        <rotationref ref="SP24F2_1inSC14rot"/>
      </physvol>
      <physvol name="SP24F3_1" copynumber="1">
        <volumeref ref="SP24F3"/>
        <positionref ref="SP24F3_1inSC14pos"/>
        <rotationref ref="SP24F3_1inSC14rot"/>
      </physvol>
      <physvol name="SV44F0_1" copynumber="1">
        <volumeref ref="SV44F0"/>
        <positionref ref="SV44F0_1inSC14pos"/>
      </physvol>
      <physvol name="SV44F1_1" copynumber="1">
        <volumeref ref="SV44F1"/>
        <positionref ref="SV44F1_1inSC14pos"/>
      </physvol>
      <physvol name="SV44F2_1" copynumber="1">
        <volumeref ref="SV44F2"/>
        <positionref ref="SV44F2_1inSC14pos"/>
        <rotationref ref="SV44F2_1inSC14rot"/>
      </physvol>
      <physvol name="SV44F3_1" copynumber="1">
        <volumeref ref="SV44F3"/>
        <positionref ref="SV44F3_1inSC14pos"/>
        <rotationref ref="SV44F3_1inSC14rot"/>
      </physvol>
      <physvol name="SH44F0_1" copynumber="1">
        <volumeref ref="SH44F0"/>
        <positionref ref="SH44F0_1inSC14pos"/>
      </physvol>
      <physvol name="SH44F1_1" copynumber="1">
        <volumeref ref="SH44F1"/>
        <positionref ref="SH44F1_1inSC14pos"/>
      </physvol>
      <physvol name="SH44F2_1" copynumber="1">
        <volumeref ref="SH44F2"/>
        <positionref ref="SH44F2_1inSC14pos"/>
        <rotationref ref="SH44F2_1inSC14rot"/>
      </physvol>
      <physvol name="SH44F3_1" copynumber="1">
        <volumeref ref="SH44F3"/>
        <positionref ref="SH44F3_1inSC14pos"/>
        <rotationref ref="SH44F3_1inSC14rot"/>
      </physvol>
      <physvol name="SHX4F0_1" copynumber="1">
        <volumeref ref="SHX4F0"/>
        <positionref ref="SHX4F0_1inSC14pos"/>
      </physvol>
      <physvol name="SHX4F1_1" copynumber="1">
        <volumeref ref="SHX4F1"/>
        <positionref ref="SHX4F1_1inSC14pos"/>
      </physvol>
      <physvol name="SHX4F2_1" copynumber="1">
        <volumeref ref="SHX4F2"/>
        <positionref ref="SHX4F2_1inSC14pos"/>
        <rotationref ref="SHX4F2_1inSC14rot"/>
      </physvol>
      <physvol name="SHX4F3_1" copynumber="1">
        <volumeref ref="SHX4F3"/>
        <positionref ref="SHX4F3_1inSC14pos"/>
        <rotationref ref="SHX4F3_1inSC14rot"/>
      </physvol>
      <physvol name="SVX4F0_1" copynumber="1">
        <volumeref ref="SVX4F0"/>
        <positionref ref="SVX4F0_1inSC14pos"/>
      </physvol>
      <physvol name="SVX4F1_1" copynumber="1">
        <volumeref ref="SVX4F1"/>
        <positionref ref="SVX4F1_1inSC14pos"/>
      </physvol>
      <physvol name="SVX4F2_1" copynumber="1">
        <volumeref ref="SVX4F2"/>
        <positionref ref="SVX4F2_1inSC14pos"/>
        <rotationref ref="SVX4F2_1inSC14rot"/>
      </physvol>
      <physvol name="SVX4F3_1" copynumber="1">
        <volumeref ref="SVX4F3"/>
        <positionref ref="SVX4F3_1inSC14pos"/>
        <rotationref ref="SVX4F3_1inSC14rot"/>
      </physvol>
    </volume>
    </structure>