<structure><volume name="Hgassipl20x8">
      <materialref ref="HMPID_CsIPCB"/>
      <solidref ref="Hgassipl20x9"/>
    </volume>
    <volume name="Hrect0x8">
      <materialref ref="HMPID_CH4"/>
      <solidref ref="Hrect0x9"/>
      <physvol name="Hgassipl2_1" copynumber="1">
        <volumeref ref="Hgassipl20x8"/>
        <positionref ref="Hgassipl2_10x4inHrect0x8pos"/>
      </physvol>
    </volume>
    <volume name="Hcufoil0x8">
      <materialref ref="HMPID_CsIPCB"/>
      <solidref ref="Hcufoil0x9"/>
      <physvol name="Hrect_0" copynumber="0">
        <volumeref ref="Hrect0x8"/>
        <positionref ref="Hrect_00x4inHcufoil0x8pos"/>
      </physvol>
      <physvol name="Hrect_10" copynumber="10">
        <volumeref ref="Hrect0x8"/>
        <positionref ref="Hrect_100x4inHcufoil0x8pos"/>
      </physvol>
      <physvol name="Hrect_20" copynumber="20">
        <volumeref ref="Hrect0x8"/>
        <positionref ref="Hrect_200x4inHcufoil0x8pos"/>
      </physvol>
      <physvol name="Hrect_30" copynumber="30">
        <volumeref ref="Hrect0x8"/>
        <positionref ref="Hrect_300x4inHcufoil0x8pos"/>
      </physvol>
      <physvol name="Hrect_40" copynumber="40">
        <volumeref ref="Hrect0x8"/>
        <positionref ref="Hrect_400x4inHcufoil0x8pos"/>
      </physvol>
      <physvol name="Hrect_50" copynumber="50">
        <volumeref ref="Hrect0x8"/>
        <positionref ref="Hrect_500x4inHcufoil0x8pos"/>
      </physvol>
      <physvol name="Hrect_60" copynumber="60">
        <volumeref ref="Hrect0x8"/>
        <positionref ref="Hrect_600x4inHcufoil0x8pos"/>
      </physvol>
      <physvol name="Hrect_70" copynumber="70">
        <volumeref ref="Hrect0x8"/>
        <positionref ref="Hrect_700x4inHcufoil0x8pos"/>
      </physvol>
      <physvol name="Hrect_1" copynumber="1">
        <volumeref ref="Hrect0x8"/>
        <positionref ref="Hrect_10x4inHcufoil0x8pos"/>
      </physvol>
      <physvol name="Hrect_11" copynumber="11">
        <volumeref ref="Hrect0x8"/>
        <positionref ref="Hrect_110x4inHcufoil0x8pos"/>
      </physvol>
      <physvol name="Hrect_21" copynumber="21">
        <volumeref ref="Hrect0x8"/>
        <positionref ref="Hrect_210x4inHcufoil0x8pos"/>
      </physvol>
      <physvol name="Hrect_31" copynumber="31">
        <volumeref ref="Hrect0x8"/>
        <positionref ref="Hrect_310x4inHcufoil0x8pos"/>
      </physvol>
      <physvol name="Hrect_41" copynumber="41">
        <volumeref ref="Hrect0x8"/>
        <positionref ref="Hrect_410x4inHcufoil0x8pos"/>
      </physvol>
      <physvol name="Hrect_51" copynumber="51">
        <volumeref ref="Hrect0x8"/>
        <positionref ref="Hrect_510x4inHcufoil0x8pos"/>
      </physvol>
      <physvol name="Hrect_61" copynumber="61">
        <volumeref ref="Hrect0x8"/>
        <positionref ref="Hrect_610x4inHcufoil0x8pos"/>
      </physvol>
      <physvol name="Hrect_71" copynumber="71">
        <volumeref ref="Hrect0x8"/>
        <positionref ref="Hrect_710x4inHcufoil0x8pos"/>
      </physvol>
      <physvol name="Hrect_2" copynumber="2">
        <volumeref ref="Hrect0x8"/>
        <positionref ref="Hrect_20x4inHcufoil0x8pos"/>
      </physvol>
      <physvol name="Hrect_12" copynumber="12">
        <volumeref ref="Hrect0x8"/>
        <positionref ref="Hrect_120x4inHcufoil0x8pos"/>
      </physvol>
      <physvol name="Hrect_22" copynumber="22">
        <volumeref ref="Hrect0x8"/>
        <positionref ref="Hrect_220x4inHcufoil0x8pos"/>
      </physvol>
      <physvol name="Hrect_32" copynumber="32">
        <volumeref ref="Hrect0x8"/>
        <positionref ref="Hrect_320x4inHcufoil0x8pos"/>
      </physvol>
      <physvol name="Hrect_42" copynumber="42">
        <volumeref ref="Hrect0x8"/>
        <positionref ref="Hrect_420x4inHcufoil0x8pos"/>
      </physvol>
      <physvol name="Hrect_52" copynumber="52">
        <volumeref ref="Hrect0x8"/>
        <positionref ref="Hrect_520x4inHcufoil0x8pos"/>
      </physvol>
      <physvol name="Hrect_62" copynumber="62">
        <volumeref ref="Hrect0x8"/>
        <positionref ref="Hrect_620x4inHcufoil0x8pos"/>
      </physvol>
      <physvol name="Hrect_72" copynumber="72">
        <volumeref ref="Hrect0x8"/>
        <positionref ref="Hrect_720x4inHcufoil0x8pos"/>
      </physvol>
      <physvol name="Hrect_3" copynumber="3">
        <volumeref ref="Hrect0x8"/>
        <positionref ref="Hrect_30x4inHcufoil0x8pos"/>
      </physvol>
      <physvol name="Hrect_13" copynumber="13">
        <volumeref ref="Hrect0x8"/>
        <positionref ref="Hrect_130x4inHcufoil0x8pos"/>
      </physvol>
      <physvol name="Hrect_23" copynumber="23">
        <volumeref ref="Hrect0x8"/>
        <positionref ref="Hrect_230x4inHcufoil0x8pos"/>
      </physvol>
      <physvol name="Hrect_33" copynumber="33">
        <volumeref ref="Hrect0x8"/>
        <positionref ref="Hrect_330x4inHcufoil0x8pos"/>
      </physvol>
      <physvol name="Hrect_43" copynumber="43">
        <volumeref ref="Hrect0x8"/>
        <positionref ref="Hrect_430x4inHcufoil0x8pos"/>
      </physvol>
      <physvol name="Hrect_53" copynumber="53">
        <volumeref ref="Hrect0x8"/>
        <positionref ref="Hrect_530x4inHcufoil0x8pos"/>
      </physvol>
      <physvol name="Hrect_63" copynumber="63">
        <volumeref ref="Hrect0x8"/>
        <positionref ref="Hrect_630x4inHcufoil0x8pos"/>
      </physvol>
      <physvol name="Hrect_73" copynumber="73">
        <volumeref ref="Hrect0x8"/>
        <positionref ref="Hrect_730x4inHcufoil0x8pos"/>
      </physvol>
      <physvol name="Hrect_4" copynumber="4">
        <volumeref ref="Hrect0x8"/>
        <positionref ref="Hrect_40x4inHcufoil0x8pos"/>
      </physvol>
      <physvol name="Hrect_14" copynumber="14">
        <volumeref ref="Hrect0x8"/>
        <positionref ref="Hrect_140x4inHcufoil0x8pos"/>
      </physvol>
      <physvol name="Hrect_24" copynumber="24">
        <volumeref ref="Hrect0x8"/>
        <positionref ref="Hrect_240x4inHcufoil0x8pos"/>
      </physvol>
      <physvol name="Hrect_34" copynumber="34">
        <volumeref ref="Hrect0x8"/>
        <positionref ref="Hrect_340x4inHcufoil0x8pos"/>
      </physvol>
      <physvol name="Hrect_44" copynumber="44">
        <volumeref ref="Hrect0x8"/>
        <positionref ref="Hrect_440x4inHcufoil0x8pos"/>
      </physvol>
      <physvol name="Hrect_54" copynumber="54">
        <volumeref ref="Hrect0x8"/>
        <positionref ref="Hrect_540x4inHcufoil0x8pos"/>
      </physvol>
      <physvol name="Hrect_64" copynumber="64">
        <volumeref ref="Hrect0x8"/>
        <positionref ref="Hrect_640x4inHcufoil0x8pos"/>
      </physvol>
      <physvol name="Hrect_74" copynumber="74">
        <volumeref ref="Hrect0x8"/>
        <positionref ref="Hrect_740x4inHcufoil0x8pos"/>
      </physvol>
      <physvol name="Hrect_5" copynumber="5">
        <volumeref ref="Hrect0x8"/>
        <positionref ref="Hrect_50x4inHcufoil0x8pos"/>
      </physvol>
      <physvol name="Hrect_15" copynumber="15">
        <volumeref ref="Hrect0x8"/>
        <positionref ref="Hrect_150x4inHcufoil0x8pos"/>
      </physvol>
      <physvol name="Hrect_25" copynumber="25">
        <volumeref ref="Hrect0x8"/>
        <positionref ref="Hrect_250x4inHcufoil0x8pos"/>
      </physvol>
      <physvol name="Hrect_35" copynumber="35">
        <volumeref ref="Hrect0x8"/>
        <positionref ref="Hrect_350x4inHcufoil0x8pos"/>
      </physvol>
      <physvol name="Hrect_45" copynumber="45">
        <volumeref ref="Hrect0x8"/>
        <positionref ref="Hrect_450x4inHcufoil0x8pos"/>
      </physvol>
      <physvol name="Hrect_55" copynumber="55">
        <volumeref ref="Hrect0x8"/>
        <positionref ref="Hrect_550x4inHcufoil0x8pos"/>
      </physvol>
      <physvol name="Hrect_65" copynumber="65">
        <volumeref ref="Hrect0x8"/>
        <positionref ref="Hrect_650x4inHcufoil0x8pos"/>
      </physvol>
      <physvol name="Hrect_75" copynumber="75">
        <volumeref ref="Hrect0x8"/>
        <positionref ref="Hrect_750x4inHcufoil0x8pos"/>
      </physvol>
      <physvol name="Hrect_6" copynumber="6">
        <volumeref ref="Hrect0x8"/>
        <positionref ref="Hrect_60x4inHcufoil0x8pos"/>
      </physvol>
      <physvol name="Hrect_16" copynumber="16">
        <volumeref ref="Hrect0x8"/>
        <positionref ref="Hrect_160x4inHcufoil0x8pos"/>
      </physvol>
      <physvol name="Hrect_26" copynumber="26">
        <volumeref ref="Hrect0x8"/>
        <positionref ref="Hrect_260x4inHcufoil0x8pos"/>
      </physvol>
      <physvol name="Hrect_36" copynumber="36">
        <volumeref ref="Hrect0x8"/>
        <positionref ref="Hrect_360x4inHcufoil0x8pos"/>
      </physvol>
      <physvol name="Hrect_46" copynumber="46">
        <volumeref ref="Hrect0x8"/>
        <positionref ref="Hrect_460x4inHcufoil0x8pos"/>
      </physvol>
      <physvol name="Hrect_56" copynumber="56">
        <volumeref ref="Hrect0x8"/>
        <positionref ref="Hrect_560x4inHcufoil0x8pos"/>
      </physvol>
      <physvol name="Hrect_66" copynumber="66">
        <volumeref ref="Hrect0x8"/>
        <positionref ref="Hrect_660x4inHcufoil0x8pos"/>
      </physvol>
      <physvol name="Hrect_76" copynumber="76">
        <volumeref ref="Hrect0x8"/>
        <positionref ref="Hrect_760x4inHcufoil0x8pos"/>
      </physvol>
      <physvol name="Hrect_7" copynumber="7">
        <volumeref ref="Hrect0x8"/>
        <positionref ref="Hrect_70x4inHcufoil0x8pos"/>
      </physvol>
      <physvol name="Hrect_17" copynumber="17">
        <volumeref ref="Hrect0x8"/>
        <positionref ref="Hrect_170x4inHcufoil0x8pos"/>
      </physvol>
      <physvol name="Hrect_27" copynumber="27">
        <volumeref ref="Hrect0x8"/>
        <positionref ref="Hrect_270x4inHcufoil0x8pos"/>
      </physvol>
      <physvol name="Hrect_37" copynumber="37">
        <volumeref ref="Hrect0x8"/>
        <positionref ref="Hrect_370x4inHcufoil0x8pos"/>
      </physvol>
      <physvol name="Hrect_47" copynumber="47">
        <volumeref ref="Hrect0x8"/>
        <positionref ref="Hrect_470x4inHcufoil0x8pos"/>
      </physvol>
      <physvol name="Hrect_57" copynumber="57">
        <volumeref ref="Hrect0x8"/>
        <positionref ref="Hrect_570x4inHcufoil0x8pos"/>
      </physvol>
      <physvol name="Hrect_67" copynumber="67">
        <volumeref ref="Hrect0x8"/>
        <positionref ref="Hrect_670x4inHcufoil0x8pos"/>
      </physvol>
      <physvol name="Hrect_77" copynumber="77">
        <volumeref ref="Hrect0x8"/>
        <positionref ref="Hrect_770x4inHcufoil0x8pos"/>
      </physvol>
      <physvol name="Hrect_8" copynumber="8">
        <volumeref ref="Hrect0x8"/>
        <positionref ref="Hrect_80x4inHcufoil0x8pos"/>
      </physvol>
      <physvol name="Hrect_18" copynumber="18">
        <volumeref ref="Hrect0x8"/>
        <positionref ref="Hrect_180x4inHcufoil0x8pos"/>
      </physvol>
      <physvol name="Hrect_28" copynumber="28">
        <volumeref ref="Hrect0x8"/>
        <positionref ref="Hrect_280x4inHcufoil0x8pos"/>
      </physvol>
      <physvol name="Hrect_38" copynumber="38">
        <volumeref ref="Hrect0x8"/>
        <positionref ref="Hrect_380x4inHcufoil0x8pos"/>
      </physvol>
      <physvol name="Hrect_48" copynumber="48">
        <volumeref ref="Hrect0x8"/>
        <positionref ref="Hrect_480x4inHcufoil0x8pos"/>
      </physvol>
      <physvol name="Hrect_58" copynumber="58">
        <volumeref ref="Hrect0x8"/>
        <positionref ref="Hrect_580x4inHcufoil0x8pos"/>
      </physvol>
      <physvol name="Hrect_68" copynumber="68">
        <volumeref ref="Hrect0x8"/>
        <positionref ref="Hrect_680x4inHcufoil0x8pos"/>
      </physvol>
      <physvol name="Hrect_78" copynumber="78">
        <volumeref ref="Hrect0x8"/>
        <positionref ref="Hrect_780x4inHcufoil0x8pos"/>
      </physvol>
      <physvol name="Hrect_9" copynumber="9">
        <volumeref ref="Hrect0x8"/>
        <positionref ref="Hrect_90x4inHcufoil0x8pos"/>
      </physvol>
      <physvol name="Hrect_19" copynumber="19">
        <volumeref ref="Hrect0x8"/>
        <positionref ref="Hrect_190x4inHcufoil0x8pos"/>
      </physvol>
      <physvol name="Hrect_29" copynumber="29">
        <volumeref ref="Hrect0x8"/>
        <positionref ref="Hrect_290x4inHcufoil0x8pos"/>
      </physvol>
      <physvol name="Hrect_39" copynumber="39">
        <volumeref ref="Hrect0x8"/>
        <positionref ref="Hrect_390x4inHcufoil0x8pos"/>
      </physvol>
      <physvol name="Hrect_49" copynumber="49">
        <volumeref ref="Hrect0x8"/>
        <positionref ref="Hrect_490x4inHcufoil0x8pos"/>
      </physvol>
      <physvol name="Hrect_59" copynumber="59">
        <volumeref ref="Hrect0x8"/>
        <positionref ref="Hrect_590x4inHcufoil0x8pos"/>
      </physvol>
      <physvol name="Hrect_69" copynumber="69">
        <volumeref ref="Hrect0x8"/>
        <positionref ref="Hrect_690x4inHcufoil0x8pos"/>
      </physvol>
      <physvol name="Hrect_79" copynumber="79">
        <volumeref ref="Hrect0x8"/>
        <positionref ref="Hrect_790x4inHcufoil0x8pos"/>
      </physvol>
    </volume>
    <volume name="Hgassipl30x8">
      <materialref ref="HMPID_CsIPCB"/>
      <solidref ref="Hgassipl30x9"/>
    </volume>
    <volume name="Hfr1upcard0x8">
      <materialref ref="HMPID_CH4"/>
      <solidref ref="Hfr1upcard0x9"/>
      <physvol name="Hgassipl3_0" copynumber="0">
        <volumeref ref="Hgassipl30x8"/>
        <positionref ref="Hgassipl3_00x4inHfr1upcard0x8pos"/>
      </physvol>
      <physvol name="Hgassipl3_10" copynumber="10">
        <volumeref ref="Hgassipl30x8"/>
        <positionref ref="Hgassipl3_100x4inHfr1upcard0x8pos"/>
      </physvol>
      <physvol name="Hgassipl3_20" copynumber="20">
        <volumeref ref="Hgassipl30x8"/>
        <positionref ref="Hgassipl3_200x4inHfr1upcard0x8pos"/>
      </physvol>
      <physvol name="Hgassipl3_30" copynumber="30">
        <volumeref ref="Hgassipl30x8"/>
        <positionref ref="Hgassipl3_300x4inHfr1upcard0x8pos"/>
      </physvol>
      <physvol name="Hgassipl3_40" copynumber="40">
        <volumeref ref="Hgassipl30x8"/>
        <positionref ref="Hgassipl3_400x4inHfr1upcard0x8pos"/>
      </physvol>
      <physvol name="Hgassipl3_50" copynumber="50">
        <volumeref ref="Hgassipl30x8"/>
        <positionref ref="Hgassipl3_500x4inHfr1upcard0x8pos"/>
      </physvol>
      <physvol name="Hgassipl3_60" copynumber="60">
        <volumeref ref="Hgassipl30x8"/>
        <positionref ref="Hgassipl3_600x4inHfr1upcard0x8pos"/>
      </physvol>
      <physvol name="Hgassipl3_70" copynumber="70">
        <volumeref ref="Hgassipl30x8"/>
        <positionref ref="Hgassipl3_700x4inHfr1upcard0x8pos"/>
      </physvol>
      <physvol name="Hgassipl3_1" copynumber="1">
        <volumeref ref="Hgassipl30x8"/>
        <positionref ref="Hgassipl3_10x4inHfr1upcard0x8pos"/>
      </physvol>
      <physvol name="Hgassipl3_11" copynumber="11">
        <volumeref ref="Hgassipl30x8"/>
        <positionref ref="Hgassipl3_110x4inHfr1upcard0x8pos"/>
      </physvol>
      <physvol name="Hgassipl3_21" copynumber="21">
        <volumeref ref="Hgassipl30x8"/>
        <positionref ref="Hgassipl3_210x4inHfr1upcard0x8pos"/>
      </physvol>
      <physvol name="Hgassipl3_31" copynumber="31">
        <volumeref ref="Hgassipl30x8"/>
        <positionref ref="Hgassipl3_310x4inHfr1upcard0x8pos"/>
      </physvol>
      <physvol name="Hgassipl3_41" copynumber="41">
        <volumeref ref="Hgassipl30x8"/>
        <positionref ref="Hgassipl3_410x4inHfr1upcard0x8pos"/>
      </physvol>
      <physvol name="Hgassipl3_51" copynumber="51">
        <volumeref ref="Hgassipl30x8"/>
        <positionref ref="Hgassipl3_510x4inHfr1upcard0x8pos"/>
      </physvol>
      <physvol name="Hgassipl3_61" copynumber="61">
        <volumeref ref="Hgassipl30x8"/>
        <positionref ref="Hgassipl3_610x4inHfr1upcard0x8pos"/>
      </physvol>
      <physvol name="Hgassipl3_71" copynumber="71">
        <volumeref ref="Hgassipl30x8"/>
        <positionref ref="Hgassipl3_710x4inHfr1upcard0x8pos"/>
      </physvol>
      <physvol name="Hgassipl3_2" copynumber="2">
        <volumeref ref="Hgassipl30x8"/>
        <positionref ref="Hgassipl3_20x4inHfr1upcard0x8pos"/>
      </physvol>
      <physvol name="Hgassipl3_12" copynumber="12">
        <volumeref ref="Hgassipl30x8"/>
        <positionref ref="Hgassipl3_120x4inHfr1upcard0x8pos"/>
      </physvol>
      <physvol name="Hgassipl3_22" copynumber="22">
        <volumeref ref="Hgassipl30x8"/>
        <positionref ref="Hgassipl3_220x4inHfr1upcard0x8pos"/>
      </physvol>
      <physvol name="Hgassipl3_32" copynumber="32">
        <volumeref ref="Hgassipl30x8"/>
        <positionref ref="Hgassipl3_320x4inHfr1upcard0x8pos"/>
      </physvol>
      <physvol name="Hgassipl3_42" copynumber="42">
        <volumeref ref="Hgassipl30x8"/>
        <positionref ref="Hgassipl3_420x4inHfr1upcard0x8pos"/>
      </physvol>
      <physvol name="Hgassipl3_52" copynumber="52">
        <volumeref ref="Hgassipl30x8"/>
        <positionref ref="Hgassipl3_520x4inHfr1upcard0x8pos"/>
      </physvol>
      <physvol name="Hgassipl3_62" copynumber="62">
        <volumeref ref="Hgassipl30x8"/>
        <positionref ref="Hgassipl3_620x4inHfr1upcard0x8pos"/>
      </physvol>
      <physvol name="Hgassipl3_72" copynumber="72">
        <volumeref ref="Hgassipl30x8"/>
        <positionref ref="Hgassipl3_720x4inHfr1upcard0x8pos"/>
      </physvol>
      <physvol name="Hgassipl3_3" copynumber="3">
        <volumeref ref="Hgassipl30x8"/>
        <positionref ref="Hgassipl3_30x4inHfr1upcard0x8pos"/>
      </physvol>
      <physvol name="Hgassipl3_13" copynumber="13">
        <volumeref ref="Hgassipl30x8"/>
        <positionref ref="Hgassipl3_130x4inHfr1upcard0x8pos"/>
      </physvol>
      <physvol name="Hgassipl3_23" copynumber="23">
        <volumeref ref="Hgassipl30x8"/>
        <positionref ref="Hgassipl3_230x4inHfr1upcard0x8pos"/>
      </physvol>
      <physvol name="Hgassipl3_33" copynumber="33">
        <volumeref ref="Hgassipl30x8"/>
        <positionref ref="Hgassipl3_330x4inHfr1upcard0x8pos"/>
      </physvol>
      <physvol name="Hgassipl3_43" copynumber="43">
        <volumeref ref="Hgassipl30x8"/>
        <positionref ref="Hgassipl3_430x4inHfr1upcard0x8pos"/>
      </physvol>
      <physvol name="Hgassipl3_53" copynumber="53">
        <volumeref ref="Hgassipl30x8"/>
        <positionref ref="Hgassipl3_530x4inHfr1upcard0x8pos"/>
      </physvol>
      <physvol name="Hgassipl3_63" copynumber="63">
        <volumeref ref="Hgassipl30x8"/>
        <positionref ref="Hgassipl3_630x4inHfr1upcard0x8pos"/>
      </physvol>
      <physvol name="Hgassipl3_73" copynumber="73">
        <volumeref ref="Hgassipl30x8"/>
        <positionref ref="Hgassipl3_730x4inHfr1upcard0x8pos"/>
      </physvol>
      <physvol name="Hgassipl3_4" copynumber="4">
        <volumeref ref="Hgassipl30x8"/>
        <positionref ref="Hgassipl3_40x4inHfr1upcard0x8pos"/>
      </physvol>
      <physvol name="Hgassipl3_14" copynumber="14">
        <volumeref ref="Hgassipl30x8"/>
        <positionref ref="Hgassipl3_140x4inHfr1upcard0x8pos"/>
      </physvol>
      <physvol name="Hgassipl3_24" copynumber="24">
        <volumeref ref="Hgassipl30x8"/>
        <positionref ref="Hgassipl3_240x4inHfr1upcard0x8pos"/>
      </physvol>
      <physvol name="Hgassipl3_34" copynumber="34">
        <volumeref ref="Hgassipl30x8"/>
        <positionref ref="Hgassipl3_340x4inHfr1upcard0x8pos"/>
      </physvol>
      <physvol name="Hgassipl3_44" copynumber="44">
        <volumeref ref="Hgassipl30x8"/>
        <positionref ref="Hgassipl3_440x4inHfr1upcard0x8pos"/>
      </physvol>
      <physvol name="Hgassipl3_54" copynumber="54">
        <volumeref ref="Hgassipl30x8"/>
        <positionref ref="Hgassipl3_540x4inHfr1upcard0x8pos"/>
      </physvol>
      <physvol name="Hgassipl3_64" copynumber="64">
        <volumeref ref="Hgassipl30x8"/>
        <positionref ref="Hgassipl3_640x4inHfr1upcard0x8pos"/>
      </physvol>
      <physvol name="Hgassipl3_74" copynumber="74">
        <volumeref ref="Hgassipl30x8"/>
        <positionref ref="Hgassipl3_740x4inHfr1upcard0x8pos"/>
      </physvol>
      <physvol name="Hgassipl3_5" copynumber="5">
        <volumeref ref="Hgassipl30x8"/>
        <positionref ref="Hgassipl3_50x4inHfr1upcard0x8pos"/>
      </physvol>
      <physvol name="Hgassipl3_15" copynumber="15">
        <volumeref ref="Hgassipl30x8"/>
        <positionref ref="Hgassipl3_150x4inHfr1upcard0x8pos"/>
      </physvol>
      <physvol name="Hgassipl3_25" copynumber="25">
        <volumeref ref="Hgassipl30x8"/>
        <positionref ref="Hgassipl3_250x4inHfr1upcard0x8pos"/>
      </physvol>
      <physvol name="Hgassipl3_35" copynumber="35">
        <volumeref ref="Hgassipl30x8"/>
        <positionref ref="Hgassipl3_350x4inHfr1upcard0x8pos"/>
      </physvol>
      <physvol name="Hgassipl3_45" copynumber="45">
        <volumeref ref="Hgassipl30x8"/>
        <positionref ref="Hgassipl3_450x4inHfr1upcard0x8pos"/>
      </physvol>
      <physvol name="Hgassipl3_55" copynumber="55">
        <volumeref ref="Hgassipl30x8"/>
        <positionref ref="Hgassipl3_550x4inHfr1upcard0x8pos"/>
      </physvol>
      <physvol name="Hgassipl3_65" copynumber="65">
        <volumeref ref="Hgassipl30x8"/>
        <positionref ref="Hgassipl3_650x4inHfr1upcard0x8pos"/>
      </physvol>
      <physvol name="Hgassipl3_75" copynumber="75">
        <volumeref ref="Hgassipl30x8"/>
        <positionref ref="Hgassipl3_750x4inHfr1upcard0x8pos"/>
      </physvol>
      <physvol name="Hgassipl3_6" copynumber="6">
        <volumeref ref="Hgassipl30x8"/>
        <positionref ref="Hgassipl3_60x4inHfr1upcard0x8pos"/>
      </physvol>
      <physvol name="Hgassipl3_16" copynumber="16">
        <volumeref ref="Hgassipl30x8"/>
        <positionref ref="Hgassipl3_160x4inHfr1upcard0x8pos"/>
      </physvol>
      <physvol name="Hgassipl3_26" copynumber="26">
        <volumeref ref="Hgassipl30x8"/>
        <positionref ref="Hgassipl3_260x4inHfr1upcard0x8pos"/>
      </physvol>
      <physvol name="Hgassipl3_36" copynumber="36">
        <volumeref ref="Hgassipl30x8"/>
        <positionref ref="Hgassipl3_360x4inHfr1upcard0x8pos"/>
      </physvol>
      <physvol name="Hgassipl3_46" copynumber="46">
        <volumeref ref="Hgassipl30x8"/>
        <positionref ref="Hgassipl3_460x4inHfr1upcard0x8pos"/>
      </physvol>
      <physvol name="Hgassipl3_56" copynumber="56">
        <volumeref ref="Hgassipl30x8"/>
        <positionref ref="Hgassipl3_560x4inHfr1upcard0x8pos"/>
      </physvol>
      <physvol name="Hgassipl3_66" copynumber="66">
        <volumeref ref="Hgassipl30x8"/>
        <positionref ref="Hgassipl3_660x4inHfr1upcard0x8pos"/>
      </physvol>
      <physvol name="Hgassipl3_76" copynumber="76">
        <volumeref ref="Hgassipl30x8"/>
        <positionref ref="Hgassipl3_760x4inHfr1upcard0x8pos"/>
      </physvol>
      <physvol name="Hgassipl3_7" copynumber="7">
        <volumeref ref="Hgassipl30x8"/>
        <positionref ref="Hgassipl3_70x4inHfr1upcard0x8pos"/>
      </physvol>
      <physvol name="Hgassipl3_17" copynumber="17">
        <volumeref ref="Hgassipl30x8"/>
        <positionref ref="Hgassipl3_170x4inHfr1upcard0x8pos"/>
      </physvol>
      <physvol name="Hgassipl3_27" copynumber="27">
        <volumeref ref="Hgassipl30x8"/>
        <positionref ref="Hgassipl3_270x4inHfr1upcard0x8pos"/>
      </physvol>
      <physvol name="Hgassipl3_37" copynumber="37">
        <volumeref ref="Hgassipl30x8"/>
        <positionref ref="Hgassipl3_370x4inHfr1upcard0x8pos"/>
      </physvol>
      <physvol name="Hgassipl3_47" copynumber="47">
        <volumeref ref="Hgassipl30x8"/>
        <positionref ref="Hgassipl3_470x4inHfr1upcard0x8pos"/>
      </physvol>
      <physvol name="Hgassipl3_57" copynumber="57">
        <volumeref ref="Hgassipl30x8"/>
        <positionref ref="Hgassipl3_570x4inHfr1upcard0x8pos"/>
      </physvol>
      <physvol name="Hgassipl3_67" copynumber="67">
        <volumeref ref="Hgassipl30x8"/>
        <positionref ref="Hgassipl3_670x4inHfr1upcard0x8pos"/>
      </physvol>
      <physvol name="Hgassipl3_77" copynumber="77">
        <volumeref ref="Hgassipl30x8"/>
        <positionref ref="Hgassipl3_770x4inHfr1upcard0x8pos"/>
      </physvol>
      <physvol name="Hgassipl3_8" copynumber="8">
        <volumeref ref="Hgassipl30x8"/>
        <positionref ref="Hgassipl3_80x4inHfr1upcard0x8pos"/>
      </physvol>
      <physvol name="Hgassipl3_18" copynumber="18">
        <volumeref ref="Hgassipl30x8"/>
        <positionref ref="Hgassipl3_180x4inHfr1upcard0x8pos"/>
      </physvol>
      <physvol name="Hgassipl3_28" copynumber="28">
        <volumeref ref="Hgassipl30x8"/>
        <positionref ref="Hgassipl3_280x4inHfr1upcard0x8pos"/>
      </physvol>
      <physvol name="Hgassipl3_38" copynumber="38">
        <volumeref ref="Hgassipl30x8"/>
        <positionref ref="Hgassipl3_380x4inHfr1upcard0x8pos"/>
      </physvol>
      <physvol name="Hgassipl3_48" copynumber="48">
        <volumeref ref="Hgassipl30x8"/>
        <positionref ref="Hgassipl3_480x4inHfr1upcard0x8pos"/>
      </physvol>
      <physvol name="Hgassipl3_58" copynumber="58">
        <volumeref ref="Hgassipl30x8"/>
        <positionref ref="Hgassipl3_580x4inHfr1upcard0x8pos"/>
      </physvol>
      <physvol name="Hgassipl3_68" copynumber="68">
        <volumeref ref="Hgassipl30x8"/>
        <positionref ref="Hgassipl3_680x4inHfr1upcard0x8pos"/>
      </physvol>
      <physvol name="Hgassipl3_78" copynumber="78">
        <volumeref ref="Hgassipl30x8"/>
        <positionref ref="Hgassipl3_780x4inHfr1upcard0x8pos"/>
      </physvol>
      <physvol name="Hgassipl3_9" copynumber="9">
        <volumeref ref="Hgassipl30x8"/>
        <positionref ref="Hgassipl3_90x4inHfr1upcard0x8pos"/>
      </physvol>
      <physvol name="Hgassipl3_19" copynumber="19">
        <volumeref ref="Hgassipl30x8"/>
        <positionref ref="Hgassipl3_190x4inHfr1upcard0x8pos"/>
      </physvol>
      <physvol name="Hgassipl3_29" copynumber="29">
        <volumeref ref="Hgassipl30x8"/>
        <positionref ref="Hgassipl3_290x4inHfr1upcard0x8pos"/>
      </physvol>
      <physvol name="Hgassipl3_39" copynumber="39">
        <volumeref ref="Hgassipl30x8"/>
        <positionref ref="Hgassipl3_390x4inHfr1upcard0x8pos"/>
      </physvol>
      <physvol name="Hgassipl3_49" copynumber="49">
        <volumeref ref="Hgassipl30x8"/>
        <positionref ref="Hgassipl3_490x4inHfr1upcard0x8pos"/>
      </physvol>
      <physvol name="Hgassipl3_59" copynumber="59">
        <volumeref ref="Hgassipl30x8"/>
        <positionref ref="Hgassipl3_590x4inHfr1upcard0x8pos"/>
      </physvol>
      <physvol name="Hgassipl3_69" copynumber="69">
        <volumeref ref="Hgassipl30x8"/>
        <positionref ref="Hgassipl3_690x4inHfr1upcard0x8pos"/>
      </physvol>
      <physvol name="Hgassipl3_79" copynumber="79">
        <volumeref ref="Hgassipl30x8"/>
        <positionref ref="Hgassipl3_790x4inHfr1upcard0x8pos"/>
      </physvol>
    </volume>
    <volume name="Hfr1up0x8">
      <materialref ref="HMPID_CH4"/>
      <solidref ref="Hfr1up0x9"/>
      <physvol name="Hcufoil_4" copynumber="4">
        <volumeref ref="Hcufoil0x8"/>
        <positionref ref="Hcufoil_40x4inHfr1up0x8pos"/>
      </physvol>
      <physvol name="Hcufoil_5" copynumber="5">
        <volumeref ref="Hcufoil0x8"/>
        <positionref ref="Hcufoil_50x4inHfr1up0x8pos"/>
      </physvol>
      <physvol name="Hcufoil_2" copynumber="2">
        <volumeref ref="Hcufoil0x8"/>
        <positionref ref="Hcufoil_20x4inHfr1up0x8pos"/>
      </physvol>
      <physvol name="Hcufoil_3" copynumber="3">
        <volumeref ref="Hcufoil0x8"/>
        <positionref ref="Hcufoil_30x4inHfr1up0x8pos"/>
      </physvol>
      <physvol name="Hcufoil_0" copynumber="0">
        <volumeref ref="Hcufoil0x8"/>
        <positionref ref="Hcufoil_00x4inHfr1up0x8pos"/>
      </physvol>
      <physvol name="Hcufoil_1" copynumber="1">
        <volumeref ref="Hcufoil0x8"/>
        <positionref ref="Hcufoil_10x4inHfr1up0x8pos"/>
      </physvol>
      <physvol name="Hfr1upcard_4" copynumber="4">
        <volumeref ref="Hfr1upcard0x8"/>
        <positionref ref="Hfr1upcard_40x4inHfr1up0x8pos"/>
      </physvol>
      <physvol name="Hfr1upcard_5" copynumber="5">
        <volumeref ref="Hfr1upcard0x8"/>
        <positionref ref="Hfr1upcard_50x4inHfr1up0x8pos"/>
      </physvol>
      <physvol name="Hfr1upcard_2" copynumber="2">
        <volumeref ref="Hfr1upcard0x8"/>
        <positionref ref="Hfr1upcard_20x4inHfr1up0x8pos"/>
      </physvol>
      <physvol name="Hfr1upcard_3" copynumber="3">
        <volumeref ref="Hfr1upcard0x8"/>
        <positionref ref="Hfr1upcard_30x4inHfr1up0x8pos"/>
      </physvol>
      <physvol name="Hfr1upcard_0" copynumber="0">
        <volumeref ref="Hfr1upcard0x8"/>
        <positionref ref="Hfr1upcard_00x4inHfr1up0x8pos"/>
      </physvol>
      <physvol name="Hfr1upcard_1" copynumber="1">
        <volumeref ref="Hfr1upcard0x8"/>
        <positionref ref="Hfr1upcard_10x4inHfr1up0x8pos"/>
      </physvol>
    </volume>
    </structure>